<?xml version="1.0" encoding="utf-8"?>
<orPrmUIRes>
  <orPrmMenu version="1.0" name="Main">
    <menuItem name="File">
      <type>popup</type>
      <label>_File</label>
      <enabled>true</enabled>
      <children>
        <menuItem name="FileNew">
          <type>action</type>
          <label>_New</label>
          <accel>Ctrl+N</accel>
          <enabled>true</enabled>
          <statusMsg>Create a new library</statusMsg>
          <id>57600</id>
        </menuItem>
        <menuItem name="FileOpen">
          <type>action</type>
          <label>_Open...</label>
          <accel>Ctrl+O</accel>
          <enabled>true</enabled>
          <statusMsg>Open an existing library</statusMsg>
          <id>57601</id>
        </menuItem>
        <menuItem name="FileClose">
          <type>action</type>
          <label>_Close</label>
          <enabled>true</enabled>
          <statusMsg>Close the active library</statusMsg>
          <id>57602</id>
        </menuItem>
        <menuItem name="FileSave">
          <type>action</type>
          <label>_Save</label>
          <accel>Ctrl+S</accel>
          <enabled>true</enabled>
          <statusMsg>Save the active library</statusMsg>
          <id>57603</id>
        </menuItem>
        <menuItem name="FileSaveAs">
          <type>action</type>
          <label>Save _As...</label>
          <enabled>true</enabled>
          <statusMsg>Save the active library with a new name</statusMsg>  
          <id>57604</id>
        </menuItem>
        <separator/>
        <menuItem name="FilePrint">
          <type>action</type>
          <label>_Print...</label>
          <accel>Ctrl+P</accel>
          <enabled>true</enabled>
          <statusMsg>Print the active model</statusMsg>
          <id>57607</id>
        </menuItem>
        <menuItem name="FilePrintPreview">
          <type>action</type>
          <label>Print Pre_view</label>
          <enabled>true</enabled>
          <statusMsg>Display full pages</statusMsg>
          <id>57609</id>
        </menuItem>
        <menuItem name="FilePageSetup">
          <type>action</type>
          <label>Page Set_up...</label>
          <enabled>true</enabled>
          <statusMsg>Change the printing options</statusMsg>
          <id>57605</id>
        </menuItem>
        <separator/>
        <menuItem name="FileExportToPartLibrary">
          <type>action</type>
          <label>Export To Part Library...</label>
          <enabled>true</enabled>
          <statusMsg>Create Capture or Design Entry HDL Parts for the Indicated Model Library</statusMsg>
          <id>14865</id>
        </menuItem>
        <menuItem name="FileModelImportWizard">
          <type>action</type>
          <label>Model Import Wizard...</label>
          <enabled>true</enabled>
          <statusMsg>Create Capture or Design Entry HDL Parts for the Indicated Model Library</statusMsg>
          <id>14866</id>
        </menuItem>
        <separator/>
        <menuItem name="FileEncryptLibrary">
          <type>action</type>
          <label>_Encrypt Library</label>
          <enabled>true</enabled>
          <statusMsg>Encrypt PSpice Library</statusMsg>
          <id>32914</id>
        </menuItem>
        <separator/>
        <menuItem name="FileRecentFile">
          <type>action</type>
          <label>Recent File</label>
          <enabled>false</enabled>
          <statusMsg>Open this document</statusMsg>
          <id>57616</id>
        </menuItem>
        <separator/>
        <menuItem name="FileExit">
          <type>action</type>
          <label>E_xit</label>
          <enabled>true</enabled>
          <statusMsg>Quit the application; prompts to save library</statusMsg>
          <id>57665</id>
        </menuItem>
      </children>
    </menuItem>
    <menuItem name="Edit">
      <type>popup</type>
      <label>_Edit</label>
      <enabled>true</enabled>
      <children>
        <menuItem name="EditCut">
          <type>action</type>
          <label>Cu_t</label>
          <enabled>true</enabled>
          <accel>Ctrl+X</accel>
          <statusMsg>Cut the selection and put it on the Clipboard</statusMsg>
          <id>57635</id>
        </menuItem>
        <menuItem name="EditCopy">
          <type>action</type>
          <label>_Copy</label>
          <enabled>true</enabled>
          <accel>Ctrl+C</accel>
          <statusMsg>Copy the selection and put it on the Clipboard</statusMsg>
          <id>57634</id>
        </menuItem>
        <menuItem name="EditPaste">
          <type>action</type>
          <label>_Paste</label>
          <enabled>true</enabled>
          <accel>Ctrl+V</accel>
          <statusMsg>Insert Clipboard contents</statusMsg>
          <id>57637</id>
        </menuItem>
        <separator/>
        <menuItem name="EditDelete">
          <type>action</type>
          <label>_Delete</label>
          <enabled>true</enabled>
          <statusMsg>Delete using the current cursor location</statusMsg>
          <id>32772</id>
        </menuItem>
        <separator/>
        <menuItem name="EditFind">
          <type>action</type>
          <label>_Find</label>
          <accel>Ctrl+F</accel>
          <enabled>true</enabled>
          <statusMsg>Find the specified text</statusMsg>
          <id>57636</id>
        </menuItem>
        <menuItem name="EditReplace">
          <type>action</type>
          <label>_Replace</label>
          <accel>Ctrl+H</accel>
          <enabled>true</enabled>
          <statusMsg>Replace specific text with different text</statusMsg>
          <id>57641</id>
        </menuItem>
      </children>
    </menuItem>
    <menuItem name="View">
      <type>popup</type>
      <label>_View</label>
      <enabled>true</enabled>
      <children>
        <menuItem name="ViewExtractModel">
          <type>action</type>
          <label>_Extract Model</label>
          <enabled>true</enabled>
          <statusMsg>View specs and graphs in customized windows</statusMsg>
          <id>32780</id>
        </menuItem>
        <menuItem name="ViewEditModel">
          <type>action</type>
          <label>E_dit Model</label>
          <enabled>true</enabled>
          <statusMsg>View Smoke and Simulation parameters for a model </statusMsg>
          <id>32860</id>
        </menuItem>
        <separator/>
        <menuItem name="ViewFit">
          <type>action</type>
          <label>_Fit</label>
          <enabled>true</enabled>
          <statusMsg>Zoom to show plot of all data</statusMsg>
          <id>32800</id>
        </menuItem>
        <menuItem name="ViewIn">
          <type>action</type>
          <label>_In</label>
          <enabled>true</enabled>
          <statusMsg>Zoom in about center of plot</statusMsg>
          <id>32801</id>
        </menuItem>
        <menuItem name="ViewOut">
          <type>action</type>
          <label>_Out</label>
          <enabled>true</enabled>
          <statusMsg>Zoom out about cursor</statusMsg>
          <id>32802</id>
        </menuItem>
        <menuItem name="ViewArea">
          <type>action</type>
          <label>_Area</label>
          <enabled>true</enabled>
          <statusMsg>Zoom to fit selected area</statusMsg>
          <id>32803</id>
        </menuItem>
        <menuItem name="ViewPrevious">
          <type>action</type>
          <label>_Previous</label>
          <enabled>true</enabled>
          <statusMsg>Use previous zoom level</statusMsg>
          <id>32804</id>
        </menuItem>
        <menuItem name="ViewRedraw">
          <type>action</type>
          <label>_Redraw</label>
          <enabled>true</enabled>
          <statusMsg>Redraw current graph</statusMsg>
          <id>32805</id>
        </menuItem>
        <menuItem name="ViewPan-NewCenter">
          <type>action</type>
          <label>Pan - New _Center</label>
          <enabled>true</enabled>
          <statusMsg>Move the center of the plot to the selected point</statusMsg>
          <id>32806</id>
        </menuItem>
        <separator/>
        <menuItem name="ViewToolbars">
          <type>action</type>
          <label>_Toolbars...</label>
          <enabled>true</enabled>
          <statusMsg>Show or hide the toolbar(s)</statusMsg>
          <id>59392</id>
        </menuItem>
        <menuItem name="ViewStatusBar">
          <type>action</type>
          <label>_Status Bar</label>
          <enabled>true</enabled>
          <statusMsg>Show or hide the status bar</statusMsg>
          <id>59393</id>
        </menuItem>
        <menuItem name="ViewModelsList">
          <type>action</type>
          <label>_Models List</label>
          <enabled>true</enabled>
          <statusMsg>Show or hide the Models List window</statusMsg>
          <id>32774</id>
        </menuItem>
        <menuItem name="ViewParameters">
          <type>action</type>
          <label>Para_meters</label>
          <enabled>true</enabled>
          <statusMsg>Show or hide the window</statusMsg>
          <id>14863</id>
        </menuItem>
      </children>
    </menuItem>
    <menuItem name="Model">
      <type>popup</type>
      <label>_Model</label>
      <enabled>true</enabled>
      <children>
        <menuItem name="ModelNew">
          <type>action</type>
          <label>_New...</label>
          <enabled>true</enabled>
          <statusMsg>Insert New Model into Library</statusMsg>
          <id>32778</id>
        </menuItem>
        <menuItem name="ModelCopyFrom">
          <type>action</type>
          <label>Copy _From...</label>
          <enabled>true</enabled>
          <statusMsg>Copy a model from another library into current library</statusMsg>
          <id>32792</id>
        </menuItem>
        <menuItem name="ModelAddSmoke">
          <type>action</type>
          <label>_Add Smoke...</label>
          <enabled>true</enabled>
          <statusMsg>Import a template to populate the grid</statusMsg>
          <id>14861</id>
        </menuItem>
        <separator/>
        <menuItem name="ModelIBISTranslator">
          <type>action</type>
          <label>IBIS _Translator...</label>
          <enabled>true</enabled>
          <action>_cdnPspIBIS2PSpice</action>
          <update>_cdnPspIBIS2PSpiceUpdate</update>
        </menuItem>
        <separator/>
        <menuItem name="ModelImport">
          <type>action</type>
          <label>Im_port...</label>
          <enabled>true</enabled>
          <statusMsg>Import a model from a file</statusMsg>
          <id>32785</id>
        </menuItem>
        <menuItem name="ModelExport">
          <type>action</type>
          <label>_Export...</label>
          <enabled>true</enabled>
          <statusMsg>Export a model to a file</statusMsg>
          <id>32786</id>
        </menuItem>
      </children>
    </menuItem>
    <menuItem name="Plot">
      <type>popup</type>
      <label>P_lot</label>
      <enabled>true</enabled>
      <children>
        <menuItem name="PlotAddTrace">
          <type>action</type>
          <label>_Add Trace...</label>
          <enabled>true</enabled>
          <statusMsg>Add a Trace to the Plot</statusMsg>
          <id>32789</id>
        </menuItem>
        <menuItem name="PlotDeleteTrace">
          <type>action</type>
          <label>_Delete Trace</label>
          <enabled>true</enabled>
          <statusMsg>Remove Trace from the Plot</statusMsg>
          <id>32807</id>
        </menuItem>
        <menuItem name="PlotAxisSettings">
          <type>action</type>
          <label>Axis _Settings...</label>
          <enabled>true</enabled>
          <statusMsg>Set X and Y Axis Values</statusMsg>
          <id>32790</id>
        </menuItem>
      </children>
    </menuItem>
    <menuItem name="Tools">
      <type>popup</type>
      <label>_Tools</label>
      <enabled>true</enabled>
      <children>
        <menuItem name="ToolsExtractParameters">
          <type>action</type>
          <label>_Extract Parameters</label>
          <enabled>true</enabled>
          <statusMsg>Extract new parameters from specifications</statusMsg>
          <id>32787</id>
        </menuItem>
        <separator/>
        <menuItem name="ToolsCustomize">
          <type>action</type>
          <label>_Customize...</label>
          <enabled>true</enabled>
          <statusMsg>Customize the toolbars and keyboard shortcuts</statusMsg>
          <id>25866</id>
        </menuItem>
        <menuItem name="ToolsOptions">
          <type>action</type>
          <label>_Options...</label>
          <enabled>true</enabled>
          <statusMsg>Set up symbol creation options</statusMsg>
          <id>32788</id>
        </menuItem>
      </children>
    </menuItem>
    <menuItem name="Window">
      <type>popup</type>
      <label>_Window</label>
      <enabled>true</enabled>
      <children>
        <menuItem name="WindowCascade">
          <type>action</type>
          <label>_Cascade</label>
          <enabled>true</enabled>
          <statusMsg>Arrange windows so they overlap</statusMsg>
          <id>57650</id>
        </menuItem>
        <menuItem name="WindowTile">
          <type>action</type>
          <label>_Tile</label>
          <enabled>true</enabled>
          <statusMsg>Arrange windows as non-overlapping tiles</statusMsg>
          <id>57651</id>
        </menuItem>
        <menuItem name="WindowArrangeIcons">
          <type>action</type>
          <label>_Arrange Icons</label>
          <enabled>true</enabled>
          <statusMsg>Arrange icons at the bottom of the window</statusMsg>
          <id>57649</id>
        </menuItem>
        <menuItem name="WindowDumpCurvesDataPoints">
          <type>action</type>
          <label>_Dump Curves Data Points</label>
          <enabled>true</enabled>
          <statusMsg>Dumps the data points for all the curves for the current device</statusMsg>
          <id>32900</id>
        </menuItem>
      </children>
    </menuItem>
    <menuItem name="Help">
      <type>popup</type>
      <label>_Help</label>
      <enabled>true</enabled>
      <children>
        <menuItem name="HelpHelpTopics">
          <type>action</type>
          <label>_Help Topics</label>
          <enabled>true</enabled>
          <statusMsg>List Help topics</statusMsg>
          <id>57666</id>
        </menuItem>
        <separator/>
        <menuItem name="HelpWebResources">
          <type>popup</type>
          <label>_Web Resources</label>
          <enabled>true</enabled>
          <children>
            <menuItem name="HelpWebResourcesCadenceOnlineSupport">
              <type>action</type>
              <label>_Cadence Online Support</label>
              <enabled>true</enabled>
              <statusMsg>Visit the SourceLink Website</statusMsg>
              <id>32903</id>
            </menuItem>
            <menuItem name="HelpWebResourcesEducationServices">
              <type>action</type>
              <label>_Education Services</label>
              <enabled>true</enabled>
              <statusMsg>Visit the Education Services Website</statusMsg>
              <id>32904</id>
            </menuItem>
            <separator/>
            <menuItem name="HelpWebResourcesPCBSystemsHome">
              <type>action</type>
              <label>_PCB Systems Home</label>
              <enabled>true</enabled>
              <statusMsg>Visit the Cadence PCB Website</statusMsg>
              <id>32905</id>
            </menuItem>
            <menuItem name="HelpWebResourcesOrCADCommunitySite">
              <type>action</type>
              <label>_OrCAD Community Site</label>
              <enabled>true</enabled>
              <statusMsg>Visit the PSpice Website</statusMsg>
              <id>32857</id>
            </menuItem>
            <separator/>
            <menuItem name="HelpWebResourcesPSpiceModelDownload">
              <type>action</type>
              <label>PSpice _Model Download</label>
              <enabled>true</enabled>
              <id>32916</id>
            </menuItem>
          </children>
        </menuItem>
        <separator/>
        <menuItem name="HelpAboutModelEditor">
          <type>action</type>
          <label>_About Model Editor...</label>
          <enabled>true</enabled>
          <statusMsg>Display program information, version number and copyright</statusMsg>
          <id>57664</id>
        </menuItem>
      </children>
    </menuItem>
  </orPrmMenu>
  <orPrmToolbar version="1.0" name="ModelEd">
    <tool name="MODELED_FILE_NEW">
      <enabled>true</enabled>
      <tooltip>New Library</tooltip>
      <id>57600</id>
      <image_16x16>16x16\MODELED_FILE_NEW.bmp</image_16x16>
      <image_24x24>24x24\MODELED_FILE_NEW.bmp</image_24x24>
    </tool>
    <tool name="MODELED_FILE_OPEN">
      <enabled>true</enabled>
      <tooltip>Open Library</tooltip>
      <id>57601</id>
      <image_16x16>16x16\MODELED_FILE_OPEN.bmp</image_16x16>
      <image_24x24>24x24\MODELED_FILE_OPEN.bmp</image_24x24>
    </tool>
    <tool name="MODELED_FILE_SAVE">
      <enabled>true</enabled>
      <tooltip>Save Library</tooltip>
      <id>57603</id>
      <image_16x16>16x16\MODELED_FILE_SAVE.bmp</image_16x16>
      <image_24x24>24x24\MODELED_FILE_SAVE.bmp</image_24x24>
    </tool>
    <tool name="MODELED_FILE_PRINT_DIRECT">
      <enabled>true</enabled>
      <statusMsg>Print the active model directly</statusMsg>
      <tooltip>Print Model Directly</tooltip>
      <id>57608</id>
      <image_16x16>16x16\MODELED_FILE_PRINT_DIRECT.bmp</image_16x16>
      <image_24x24>24x24\MODELED_FILE_PRINT_DIRECT.bmp</image_24x24>
    </tool>
    <tool name="MODELED_FILE_PRINT_PREVIEW">
      <enabled>true</enabled>
      <tooltip>Print Preview</tooltip>
      <id>57609</id>
      <image_16x16>16x16\MODELED_FILE_PRINT_PREVIEW.bmp</image_16x16>
      <image_24x24>24x24\MODELED_FILE_PRINT_PREVIEW.bmp</image_24x24>
    </tool>
    <separator/>
    <tool name="MODELED_FILE_ENCRYPTLIBRARY">
      <enabled>true</enabled>
      <tooltip>Encrypt Library</tooltip>
      <id>32914</id>
      <image_16x16>16x16\MODELED_FILE_ENCRYPTLIBRARY.bmp</image_16x16>
      <image_24x24>24x24\MODELED_FILE_ENCRYPTLIBRARY.bmp</image_24x24>
    </tool>
    <separator/>
    <tool name="MODELED_EDIT_CUT">
      <enabled>true</enabled>
      <tooltip>Cut</tooltip>
      <id>57635</id>
      <image_16x16>16x16\MODELED_EDIT_CUT.bmp</image_16x16>
      <image_24x24>24x24\MODELED_EDIT_CUT.bmp</image_24x24>
    </tool>
    <tool name="MODELED_EDIT_COPY">
      <enabled>true</enabled>
      <tooltip>Copy</tooltip>
      <id>57634</id>
      <image_16x16>16x16\MODELED_EDIT_COPY.bmp</image_16x16>
      <image_24x24>24x24\MODELED_EDIT_COPY.bmp</image_24x24>
    </tool>
    <tool name="MODELED_EDIT_PASTE">
      <enabled>true</enabled>
      <tooltip>Paste</tooltip>
      <id>57637</id>
      <image_16x16>16x16\MODELED_EDIT_PASTE.bmp</image_16x16>
      <image_24x24>24x24\MODELED_EDIT_PASTE.bmp</image_24x24>
    </tool>
    <separator/>
    <tool name="MODELED_VIEW_IN">
      <enabled>true</enabled>
      <tooltip>Zoom In</tooltip>
      <id>32801</id>
      <image_16x16>16x16\MODELED_VIEW_IN.bmp</image_16x16>
      <image_24x24>24x24\MODELED_VIEW_IN.bmp</image_24x24>
    </tool>
    <tool name="MODELED_VIEW_OUT">
      <enabled>true</enabled>
      <tooltip>Zoom Out</tooltip>
      <id>32802</id>
      <image_16x16>16x16\MODELED_VIEW_OUT.bmp</image_16x16>
      <image_24x24>24x24\MODELED_VIEW_OUT.bmp</image_24x24>
    </tool>
    <tool name="MODELED_VIEW_AREA">
      <enabled>true</enabled>
      <tooltip>Zoom Area</tooltip>
      <id>32803</id>
      <image_16x16>16x16\MODELED_VIEW_AREA.bmp</image_16x16>
      <image_24x24>24x24\MODELED_VIEW_AREA.bmp</image_24x24>
    </tool>
    <tool name="MODELED_VIEW_FIT">
      <enabled>true</enabled>
      <tooltip>Zoom to Fit Data</tooltip>
      <id>32800</id>
      <image_16x16>16x16\MODELED_VIEW_FIT.bmp</image_16x16>
      <image_24x24>24x24\MODELED_VIEW_FIT.bmp</image_24x24>
    </tool>
    <separator/>
    <tool name="MODELED_MODEL_NEW">
      <enabled>true</enabled>
      <tooltip>New Model</tooltip>
      <id>32778</id>
      <image_16x16>16x16\MODELED_MODEL_NEW.bmp</image_16x16>
      <image_24x24>24x24\MODELED_MODEL_NEW.bmp</image_24x24>
    </tool>
    <separator/>
    <tool name="MODELED_PLOT_LOG_X">
      <enabled>true</enabled>
      <statusMsg>Toggle X Axis between Log and Linear Scale</statusMsg>
      <tooltip>Toggle X</tooltip>
      <id>32798</id>
      <image_16x16>16x16\MODELED_PLOT_LOG_X.bmp</image_16x16>
      <image_24x24>24x24\MODELED_PLOT_LOG_X.bmp</image_24x24>
    </tool>
    <tool name="MODELED_PLOT_LOG_Y">
      <enabled>true</enabled>
      <statusMsg>Toggle Y Axis between Log and Linear Scale</statusMsg>
      <tooltip>Toggle Y</tooltip>
      <id>32799</id>
      <image_16x16>16x16\MODELED_PLOT_LOG_Y.bmp</image_16x16>
      <image_24x24>24x24\MODELED_PLOT_LOG_Y.bmp</image_24x24>
    </tool>
    <separator/>
    <tool name="MODELED_TOOLS_EXTRACT">
      <enabled>true</enabled>
      <tooltip>Extract</tooltip>
      <id>32787</id>
      <image_16x16>16x16\MODELED_TOOLS_EXTRACT.bmp</image_16x16>
      <image_24x24>24x24\MODELED_TOOLS_EXTRACT.bmp</image_24x24>
    </tool>
    <tool name="MODELED_HIDDEN_SYNC_SPLITTERS">
      <enabled>true</enabled>
      <statusMsg>Synchronize Spec Window Splitter Bars</statusMsg>
      <tooltip>Sync Splitters</tooltip>
      <id>32791</id>
      <image_16x16>16x16\MODELED_HIDDEN_SYNC_SPLITTERS.bmp</image_16x16>
      <image_24x24>24x24\MODELED_HIDDEN_SYNC_SPLITTERS.bmp</image_24x24>
    </tool>
    <tool name="MODELED_UPDATE_GRAPH">
      <enabled>true</enabled>
      <statusMsg>Update the graph</statusMsg>
      <tooltip>Update Graph</tooltip>
      <id>32797</id>
      <image_16x16>16x16\MODELED_UPDATE_GRAPH.bmp</image_16x16>
      <image_24x24>24x24\MODELED_UPDATE_GRAPH.bmp</image_24x24>
    </tool>
    <tool name="MODELED_UPDATE_GRAPH_AUTOMATICALLY">
      <enabled>true</enabled>
      <statusMsg>Refresh Graph automatically after a change</statusMsg>
      <tooltip>Auto Refresh</tooltip>
      <id>32815</id>
      <image_16x16>16x16\MODELED_UPDATE_GRAPH_AUTOMATICALLY.bmp</image_16x16>
      <image_24x24>24x24\MODELED_UPDATE_GRAPH_AUTOMATICALLY.bmp</image_24x24>
    </tool>
  </orPrmToolbar>
</orPrmUIRes>