<?xml version="1.0"?>

<MsgFile>

  <Msg>

    <CDNUSR_DEFINE_NAME>eORSCHIF_E_REG_INFO_ERR</CDNUSR_DEFINE_NAME>

    <Id>16001</Id>

    <Category>E</Category>

    <Desc>"Error in reg info.&#xA;"</Desc>

    <Output>U</Output>

    <ExtDesc>""</ExtDesc>

  </Msg>

  <Msg>

    <CDNUSR_DEFINE_NAME>eORSCHIF_E_DSN_OPEN_ERR</CDNUSR_DEFINE_NAME>

    <Id>16002</Id>

    <Category>E</Category>

    <Desc>"Unable to open Design "%s"&#xA;Not a recognized Design(.DSN) file."</Desc>

    <Output>U</Output>

    <ExtDesc>""</ExtDesc>

  </Msg>

  <Msg>

    <CDNUSR_DEFINE_NAME>eORSCHIF_E_WARN_DUP_TITLE_BLOCKS</CDNUSR_DEFINE_NAME>

    <Id>16003</Id>

    <Category>E</Category>

    <Desc>"%d title blocks found on page %s, using the last one found.&#xA;"</Desc>

    <Output>U</Output>

    <ExtDesc>""</ExtDesc>

  </Msg>

  <Msg>

    <CDNUSR_DEFINE_NAME>eORSCHIF_I_GRP_DATA_LTD</CDNUSR_DEFINE_NAME>

    <Id>16004</Id>

    <Category>I</Category>

    <Desc>"Group data size has exceeded file size.&#xA;Continue Reading Data(Yes/No).&#xA;Option No reads data equal to file size."</Desc>

    <Output>U</Output>

    <ExtDesc>""</ExtDesc>

  </Msg>

  <Msg>

    <CDNUSR_DEFINE_NAME>eORSCHIF_I_GRP_DATA_LIMIT</CDNUSR_DEFINE_NAME>

    <Id>16005</Id>

    <Category>I</Category>

    <Desc>"'%s' Group data size has exceeded %d size.&#xA;Group data may be corrupt.&#xA;Continue Reading Data(Yes/No).Option No ignores this Group and will continue reading other groups."</Desc>

    <Output>U</Output>

    <ExtDesc>""</ExtDesc>

  </Msg>

  <Msg>

    <CDNUSR_DEFINE_NAME>eORSCHIF_E_ERR_FOPEN_READ</CDNUSR_DEFINE_NAME>

    <Id>16008</Id>

    <Category>E</Category>

    <Desc>"File [%s] not found.&#xA;"</Desc>

    <Output>U</Output>

    <ExtDesc>""</ExtDesc>

  </Msg>

  <Msg>

    <CDNUSR_DEFINE_NAME>eORSCHIF_E_ERR_FOPEN_WRITE</CDNUSR_DEFINE_NAME>

    <Id>16009</Id>

    <Category>E</Category>

    <Desc>"Unable to write file %s.&#xA;"</Desc>

    <Output>U</Output>

    <ExtDesc>""</ExtDesc>

  </Msg>

  <Msg>

    <CDNUSR_DEFINE_NAME>eORSCHIF_E_ERR_FOPEN</CDNUSR_DEFINE_NAME>

    <Id>16010</Id>

    <Category>E</Category>

    <Desc>"fopen() error on file %s.&#xA;"</Desc>

    <Output>U</Output>

    <ExtDesc>""</ExtDesc>

  </Msg>

  <Msg>

    <CDNUSR_DEFINE_NAME>eORSCHIF_I_SHOW_WARNING</CDNUSR_DEFINE_NAME>

    <Id>16011</Id>

    <Category>Q</Category>

    <Desc>"Warnings have been Issued.&#xA;Would you like to view the Session now?"</Desc>

    <Output>U</Output>

    <ExtDesc>""</ExtDesc>

  </Msg>

  <Msg>

    <CDNUSR_DEFINE_NAME>eORSCHIF_E_FILE_OPEN_ERR</CDNUSR_DEFINE_NAME>

    <Id>16012</Id>

    <Category>E</Category>

    <Desc>"Error opening file %s&#xA;"</Desc>

    <Output>U</Output>

    <ExtDesc>""</ExtDesc>

  </Msg>

  <Msg>

    <CDNUSR_DEFINE_NAME>eORSCHIF_E_SYM_LIB_ERR</CDNUSR_DEFINE_NAME>

    <Id>16013</Id>

    <Category>E</Category>

    <Desc>"Error getting symbol library %s: %s"</Desc>

    <Output>U</Output>

    <ExtDesc>""</ExtDesc>

  </Msg>

  <Msg>

    <CDNUSR_DEFINE_NAME>eORSCHIF_E_LIB_NOT_FOUND</CDNUSR_DEFINE_NAME>

    <Id>16014</Id>

    <Category>E</Category>

    <Desc>"Lib not found"</Desc>

    <Output>U</Output>

    <ExtDesc>""</ExtDesc>

  </Msg>

  <Msg>

    <CDNUSR_DEFINE_NAME>eORSCHIF_E_SRC_MAP_UPDATION_THEAD</CDNUSR_DEFINE_NAME>

    <Id>16015</Id>

    <Category>E</Category>

    <Desc>"This is the Map Updation Thead &#xA;"</Desc>

    <Output>U</Output>

    <ExtDesc>""</ExtDesc>

  </Msg>

  <Msg>

    <CDNUSR_DEFINE_NAME>eORSCHIF_E_SRC_MAIN_THREAD_WAITING_LOCK</CDNUSR_DEFINE_NAME>

    <Id>16016</Id>

    <Category>E</Category>

    <Desc>"This is the main thread : waiting for Lock &#xA;"</Desc>

    <Output>U</Output>

    <ExtDesc>""</ExtDesc>

  </Msg>

  <Msg>

    <CDNUSR_DEFINE_NAME>eORSCHIF_E_SRC_UPDATEMAP_PROCESSING_LIBRARY</CDNUSR_DEFINE_NAME>

    <Id>16017</Id>

    <Category>E</Category>

    <Desc>"UpdateMap(): Processing Library %s...&#xA;"</Desc>

    <Output>U</Output>

    <ExtDesc>""</ExtDesc>

  </Msg>

  <Msg>

    <CDNUSR_DEFINE_NAME>eORSCHIF_I_SRC_KEY_VALUE</CDNUSR_DEFINE_NAME>

    <Id>16019</Id>

    <Category>I</Category>

    <Desc>"Key = %s, Value = %lx&#xA;"</Desc>

    <Output>U</Output>

    <ExtDesc>""</ExtDesc>

  </Msg>

  <Msg>

    <CDNUSR_DEFINE_NAME>eORSCHIF_I_SRC_STUFF_LIST_SIZE</CDNUSR_DEFINE_NAME>

    <Id>16023</Id>

    <Category>I</Category>

    <Desc>"Not Stuff List Size = %d"</Desc>

    <Output>U</Output>

    <ExtDesc>""</ExtDesc>

  </Msg>

</MsgFile>